{
    "Coordinates": [
        "55.14150600",
        "37.45730400"
    ],
    "additional_url": "/msk/place/2-tone-bar",
    "address": "Чехов, Чехова, 79к4",
    "avg_check": "400  (без напитков)",
    "category": "Бар",
    "description": "\n                Крафтовый бар в Чехове. Девиз заведения: Beer, Burgers, Music! Что в переводе означает «пиво, бургеры, музыка». В зале 2Tone Bar на улице Чехова контактная барная стойка и концертная сцена, на которой по вечерам выступают музыканты и комики в формате открытый микрофон. В баре устраивают кинопоказы, спортивные трансляции и пабквизы. В меню «Тут он бара» крафт от отечественных и европейских пивоварен. В пару к пиву подают бургеры, колбаски, а для вегетарианцев предусмотрен фалафель в пите.                            ",
    "features": [
        "здесь танцуют",
        "за городом",
        "живая музыка",
        "спортивные трансляции"
    ],
    "kitchen": [
        "американская",
        "европейская"
    ],
    "main_image_url": "",
    "main_url": "https://www.restoclub.ru",
    "name": "2 Tone Bar",
    "phone": "+79017409546",
    "timetable": "Пн–Вс: C 18:00 — до последнего гостя"
}