{
    "Coordinates": [
        "59.93535800",
        "30.36065800"
    ],
    "additional_url": "/spb/place/akyan",
    "address": "ул. Восстания 19",
    "album": "complete",
    "avg_check": "1300  (без напитков)",
    "category": "Ресторан",
    "description": "\n                Небольшой ресторан при одноименном отеле на Восстании. По будням с 7:00 до 11:00 и по выходным с 8:00 до 12:00 действует меню завтраков, которое меняется каждый день. В основное меню вошли популярные блюда европейской кухни. Интерьер выполнен в стиле английского лофта с элементами арт деко. В ресторане два зала на 35 и 15 посадочных мест, в одном из них есть старинный камин.                            ",
    "features": [
        "при отеле",
        "кальян",
        "камин"
    ],
    "kitchen": [
        "европейская"
    ],
    "main_image_url": "akyan+main_image.jpg",
    "main_url": "https://www.restoclub.ru",
    "menu": "complete",
    "name": "Akyan",
    "phone": "+78124264004",
    "timetable": "Пн–Вс: Круглосуточно"
}