{
    "Coordinates": [
        "59.91012200",
        "30.51495300"
    ],
    "additional_url": "/spb/place/beer-sommelier",
    "address": "Европейский пр. 21к2",
    "album": "complete",
    "avg_check": "500  (без напитков)",
    "category": "Бар",
    "description": "\n                Пивной бар на Европейском проспекте в Кудрово.                            ",
    "features": [
        "спортивные трансляции"
    ],
    "kitchen": [
        "стритфуд",
        "европейская",
        "крафтовое пиво"
    ],
    "main_image_url": "beer-sommelier+main_image.jpg",
    "main_url": "https://www.restoclub.ru",
    "menu": "complete",
    "name": "Beer Sommelier",
    "phone": "+79955957245",
    "timetable": "Пн–Чт: 15:00 — 00:00Пт–Сб: 15:00 — 02:00Вс: 15:00 — 00:00"
}