{
    "Coordinates": [
        "55.96660676",
        "37.41656860"
    ],
    "additional_url": "/msk/place/beluga-caviar-bar-1",
    "address": "Аэропорт Шереметьево ",
    "avg_check": "1800  (без напитков)",
    "category": "Ресторан",
    "description": "\n                Нарядный бар алкогольного бренда в Шереметьево. Beluga Caviar Bar находится на третьем этаже аэропорта, в зоне вылета международных рейсов, в терминале C. В барную карту добавили коллекцию крепкого алкоголя, немного вина и разные вариации водки бренда, в том числе Gold Line, которую делают с настоем риса и выпускают ограниченными тиражами. В меню бара «Белуга» собрали оригинальные закуски из тунца и краба, делают роллы, японские тартары, поке и икорные сеты.                            ",
    "features": [
        "чаевые онлайн"
    ],
    "kitchen": [
        "рыба и морепродукты",
        "коктейли"
    ],
    "main_image_url": "",
    "main_url": "https://www.restoclub.ru",
    "name": "Beluga Caviar Bar",
    "phone": "+79773736559",
    "timetable": "Пн–Вс: Круглосуточно"
}