{
    "Coordinates": [
        "59.84920200",
        "30.14424500"
    ],
    "additional_url": "/spb/place/budu-pozdno",
    "address": "Петергофское шоссе 51",
    "album": "complete",
    "avg_check": "1100  (без напитков)",
    "category": "Бар",
    "description": "\n                Караоке-бар в ТРЦ «Жемчужная плаза». В «Буду поздно» проводят вечеринки и поют караоке. В широкой барной карте, помимо коллекции крепкого алкоголя, есть фруктовое пиво, фламандский эль и сидр. Можно заказать больше 30 коктейлей, в том числе горячие и безалкогольные варианты. К напиткам подают гренки, креветки в темпуре и сырные шарики. Из основных блюд готовят рыбные и мясные позиции, несколько вариантов салатов и супов. На стенах бара изобразили героев «Симпосонов» и «Футурамы» и установили неоновые надписи.                            ",
    "features": [
        "чаевые онлайн",
        "караоке"
    ],
    "kitchen": [
        "коктейли"
    ],
    "main_image_url": "budu-pozdno+main_image.jpg",
    "main_url": "https://www.restoclub.ru",
    "menu": "complete",
    "name": "Буду поздно",
    "phone": "+79819725907",
    "timetable": "Пн–Чт: 12:00 — 02:00Пт–Сб: 12:00 — 06:00Вс: 12:00 — 02:00"
}