{
    "Coordinates": [
        "55.75431531",
        "37.63759577"
    ],
    "additional_url": "/msk/place/bushe-31",
    "address": "ул. Солянка 1/2 стр.1",
    "avg_check": "700  (без напитков)",
    "category": "Кафе",
    "description": "\n                Флагманское кафе-кондитерская на Солянке.  Здесь выпекают около 10 видов хлеба,  десерты, слойки и торты на заказ. Помимо этого, готовят домашнюю пасту, европейские крем-супы, салаты и сэндвичи.  По утрам в «Буше» сервируют завтраки с омлетами, кашами на безлактозном молоке  и сырниками. Из напитков — кофейная классика, фирменные чайные напитки, фреши и смузи.                            ",
    "features": [
        "чаевые онлайн",
        "завтрак"
    ],
    "kitchen": [
        "торты на заказ",
        "европейская",
        "десерты"
    ],
    "main_image_url": "",
    "main_url": "https://www.restoclub.ru",
    "name": "Буше",
    "phone": "+74956406006",
    "timetable": "Пн–Вс: 10:00 — 21:00"
}