{
    "Coordinates": [
        "59.93416800",
        "30.31295800"
    ],
    "additional_url": "/spb/place/butcher-house",
    "address": "ул. Большая Морская 25",
    "album": "complete",
    "avg_check": "2000  (без напитков)",
    "category": "Ресторан",
    "description": "\n                «Дом мясника» — мясной ресторан на Большой Морской улице. \r\nРесторан занимает три зала и вмещает порядка 60 гостей: первый — основной с открытой кухней, двумя винными шкафами, камерой сухого вызревания мяса и окнами, выходящими на Большую Морскую; второй — с контактной барной стойкой и со столами для больших компаний; третий — под мероприятия.\r\nВ меню — преимущественно мясные блюда: в хоспере готовят стейки, брискет, ребрышки и полдюжины колбас собственного производства. Барная карта включает чуть меньше десяти сортов разливного пива и более 50 позиций демократичных вин.                            ",
    "features": [
        "завтрак",
        "доставка"
    ],
    "kitchen": [
        "европейская",
        "стейки",
        "бургеры"
    ],
    "main_image_url": "butcher-house+main_image.jpg",
    "main_url": "https://www.restoclub.ru",
    "menu": "complete",
    "name": "Дом мясника",
    "phone": "+78122007300",
    "timetable": "Пн–Чт: 10:00 — 23:00Пт–Сб: 10:00 — 00:00Вс: 10:00 — 23:00"
}