{
    "Coordinates": [
        "55.76629960",
        "37.60757260"
    ],
    "additional_url": "/msk/place/chajhona-1-13",
    "address": "пл. Пушкинская 2",
    "avg_check": "2000  (без напитков)",
    "category": "Ресторан",
    "description": "\n                Vasilchuki Chaihona №1 — ресторан популярной сети заведений узбекской кухни. \r\n«Чайхона №1» – место для расслабленного отдыха. Кухня, кроме обязательных национальных блюд, предлагает европейский и японский ассортименты. В баре есть любой алкоголь. Интерьеры утрированно-восточные: ковры, подносы, кувшины и расписанная керамика. Колорит Средней Азии поддерживают исполнение танца живота и бестабачные паровые коктейли. Веселье подогревает зал караоке.                            ",
    "features": [
        "караоке",
        "детская комната",
        "кальян",
        "доставка",
        "парковка"
    ],
    "kitchen": [
        "узбекская",
        "европейская"
    ],
    "main_image_url": "",
    "main_url": "https://www.restoclub.ru",
    "name": "Vasilchuki Chaihona №1",
    "phone": "+74952340233",
    "timetable": "Пн–Вс: 11:00 — 06:00"
}