{
    "Coordinates": [
        "55.77904900",
        "37.58860200"
    ],
    "additional_url": "/msk/place/cheese-connection",
    "address": "ул. Лесная 9",
    "avg_check": "2000  (без напитков)",
    "category": "Ресторан",
    "description": "\n                Ресторан с собственной сыроварней на Лесной улице. Cheese Connection — это ресторан от создателей сети «Простые вещи». В меню здесь представили несколько разделов: закуски к вину, салаты, супы, горячее, фондю, десерты. В каждом блоке отдельно отметили блюда от ресторана Cheese Connection и ресторана «Простые вещи». В «Чиз коннекшн» производят халуми, черную страчателлу, сладкую моцареллу и активно добавляют их в блюда. Из фирменного — буррата с красной икрой и картофельным гратеном; ризотто с камамбером, маскарпоне, пеной из сыра с голубой плесенью. Интерьер в ресторане строгий и местами может показаться брутальным. Здесь грубые бетонные стены, тяжелая мебель, на потолке красуются лампы, созданные при помощи 3D-принтера.                            ",
    "features": [
        "заказ кейтеринга",
        "бранч"
    ],
    "kitchen": [
        "европейская"
    ],
    "main_image_url": "",
    "main_url": "https://www.restoclub.ru",
    "name": "Cheese Connection",
    "phone": "+74957807585",
    "timetable": "Пн–Вс: 12:00 — 00:00"
}