{
    "Coordinates": [
        "59.92498400",
        "30.36231100"
    ],
    "additional_url": "/spb/place/drink-drank-drunk",
    "address": "пр. Лиговский 50Д",
    "album": "complete",
    "avg_check": "1000  (без напитков)",
    "category": "Паб",
    "description": "\n                Пивной бар с кинопросмотрами на Лиговском проспекте. На кранах здесь разливают крафтовые позиции российского производства. Помимо разливного подают бутылочные и баночные варианты. В сопровождение к напиткам готовят популярные закуски и блюда европейской кухни. Для начала предлагают креветки фри, гренки и куриные крылья в соусе кимчи, а на горячее — томленые говяжьи щечки и сытный драник с соусом на выбор. По будням действует специальное меню для бизнес-ланча. По выходным организуют вечеринки и кинопоказы.                            ",
    "features": [
        "здесь танцуют",
        "бизнес-ланч",
        "dj",
        "спортивные трансляции",
        "своя пивоварня"
    ],
    "kitchen": [
        "европейская",
        "крафтовое пиво"
    ],
    "main_image_url": "drink-drank-drunk+main_image.jpg",
    "main_url": "https://www.restoclub.ru",
    "menu": "complete",
    "name": "Drink Drank Drunk",
    "phone": "+79291160988",
    "timetable": "Пн–Чт: 12:00 — 23:00Пт: 12:00 — 02:00Сб: 13:00 — 02:00Вс: 13:00 — 23:00"
}