{
    "Coordinates": [
        "55.75613966",
        "37.56144463"
    ],
    "additional_url": "/msk/place/druzhba-5",
    "address": "ул. Рочдельская 15с30",
    "avg_check": "2600  (без напитков)",
    "category": "Ресторан",
    "description": "\n                «Дружба» — стильный ресторан на Трехгорке. \r\nПроект запустил холдинг Soho Family в 2017 году. Ресторан расположился в просторном лофте с деревянно-кирпичными стенами и огромными окнами. Еженедельно по пятницам и субботам в ресторане проходят иммерсивные театральные представления. Актеры разыгрывают сценки прямо в зале ресторана, и гости оказываются вовлеченными в происходящее. \r\nДолжность шеф-повара занимает Иван Яковлев, работавший под началом знаменитого  французского шефа Пьера Гарньера ― апологета новой французской кухни, молекулярной гастрономии и кулинарного направления фьюжн. Здешнее меню полностью отражает название: в списке «подружили» ностальгический оливье, итальянскую пасту, бургеры  и колбаски собственного производства. \r\nВ баре предлагают сеты из 10, 20, 30 или 50 шотов. Все они довольно легкие, содержат в себе фруктовые пюре и соки. Отдельно в карте представлены спритцы: помимо привычного уже апероля, есть еще четыре разновидности. Вино ― преимущественно Франция и Италия, но есть и представители других стран. Из крепкого алкоголя сконцентрировались на виски.                            ",
    "features": [
        "чаевые онлайн",
        "еда навынос",
        "живая музыка",
        "бизнес-ланч",
        "dj"
    ],
    "kitchen": [
        "европейская",
        "русская",
        "смешанная",
        "итальянская",
        "азиатская"
    ],
    "main_image_url": "",
    "main_url": "https://www.restoclub.ru",
    "name": "Дружба",
    "phone": "+74951201133",
    "timetable": "Пн–Ср: 12:00 — 00:00Чт–Вс: 12:00 — 06:00"
}