{
    "Coordinates": [
        "59.93255030",
        "30.32138532"
    ],
    "additional_url": "/spb/place/dvor-kultury",
    "address": "ул. Казанская 7",
    "album": "complete",
    "avg_check": "1400  (без напитков)",
    "category": "Бар",
    "description": "\n                «Двор культуры» — бар с танцевальной площадкой на Казанской улице. \r\nЗаведение сочетает в себе формат бара и клуба. В залы ведет коридор, оформленный под грузовой контейнер, а стены украшают граффити. Само пространство поделили на две зоны: лаунж-бар с кальянами и танцевальную площадку. Из музыкальных направлений ориентируются на хип-хоп, джаз, соул и фанк. За меню отвечает Кирилл Зотов, шеф-повар ресторана Department 57, под его руководством готовят несколько вариантов закусок, хот-доги, стейки и десерты. Периодически в «ДК» устраивают вечеринки с диджейскими сетами.                            ",
    "features": [
        "здесь танцуют"
    ],
    "kitchen": [
        "коктейли",
        "стейки",
        "европейская"
    ],
    "main_image_url": "dvor-kultury+main_image.jpg",
    "main_url": "https://www.restoclub.ru",
    "menu": "complete",
    "name": "Двор культуры",
    "phone": "+79218846644",
    "timetable": "Пн–Чт: ВыходнойПт–Сб: 23:00 — 06:00Вс: Выходной"
}