{
    "Coordinates": [
        "59.92958346",
        "30.28821253"
    ],
    "additional_url": "/spb/place/dzamiko",
    "address": "наб. Адмиралтейского канала  2",
    "album": "complete",
    "avg_check": "1300  (без напитков)",
    "category": "Кафе",
    "description": "\n                Грузинское кафе в здании «Бутылка» на Новой Голландии. «Дзамико» принадлежит владельцам японских бистро Ronny и Gills. Меню кафе уместилось на одной странице, но в нем представлены практически все хиты грузинской кухни: пхали, баклажаны с орехами, салаты с ореховой заправкой, хинкали, хачапури, лобио. На десерт, к примеру, можно взять мацони — традиционный кисломолочный напиток, который подают с медом и орехами. В барной карте акцент сделали на биодинамические вина. Основной зал с открытой кухней оформлен в стиле индустриального лофта: бетонные стены, вентиляционные короба, открытая кирпичная кладка, обилие зелени и антикварная мебель.                            ",
    "features": [
        "чаевые онлайн",
        "доставка"
    ],
    "kitchen": [
        "кавказская",
        "грузинская"
    ],
    "main_image_url": "dzamiko+main_image.jpg",
    "main_url": "https://www.restoclub.ru",
    "menu": "complete",
    "name": "Дзамико",
    "phone": "+79219156149",
    "timetable": "Пн–Вс: 10:30 — 23:00"
}