{
    "Coordinates": [
        "55.77193500",
        "37.25247900"
    ],
    "additional_url": "/msk/place/fabrika-andy",
    "address": "дер. Глухово, Центральная 43",
    "avg_check": "1400  (без напитков)",
    "category": "Ресторан",
    "description": "\n                Ресторан европейской кухни в деревне Глухово. Кроме салатов, пасты и пиццы в  «Фабрике Andy» предлагают большой выбор ароматных мясных блюд с мангала: люля-кебаб, корейку баранины, стейк из лосося или дорадо на углях. Каждый день готовят завтраки: блины, омлеты, каши. Можно взять и готовый сет в стиле завтраков разных стран мира: голландский, китайский или английский завтрак. Ресторан «Фабрика Энди» расположен на втором этаже одноименного фудмаркета и занимает просторный зал.                            ",
    "features": [
        "доставка"
    ],
    "kitchen": [
        "европейская"
    ],
    "main_image_url": "",
    "main_url": "https://www.restoclub.ru",
    "name": "Фабрика Andy",
    "phone": "+79800007700",
    "timetable": "Пн–Вс: 09:00 — 23:00"
}