{
    "Coordinates": [
        "55.78021300",
        "37.59307500"
    ],
    "additional_url": "/msk/place/fifteen-pizzeria",
    "address": "ул. Лесная 20 стр.3",
    "avg_check": "800  (без напитков)",
    "category": "Корнер",
    "description": "\n                Корнер с римской пиццей в \"Депо\".                            ",
    "features": [],
    "kitchen": [
        "пицца",
        "итальянская"
    ],
    "main_image_url": "",
    "main_url": "https://www.restoclub.ru",
    "name": "Fifteen Pizzeria",
    "phone": "+74957888810",
    "timetable": "Пн–Чт: 10:00 — 23:00Пт–Сб: 10:00 — 02:00Вс: 10:00 — 23:00"
}