{
    "Coordinates": [
        "59.93031300",
        "30.37019800"
    ],
    "additional_url": "/spb/place/friends-of-friends",
    "address": "ул. Дегтярная 1",
    "album": "complete",
    "avg_check": "1800  (без напитков)",
    "category": "Ресторан",
    "description": "\n                Friends of Friends — итальянский ресторан с ранними завтраками на Дегтярной улице. \r\nВнутри — стильный интерьер с историческими арочными большими окнами, стенами в стиле лофт и мягким освещением. В качестве декора — стеллажи с вином и большая декорация в виде сухоцветов на потолке.\r\nС 8 утра в заведении кормят блюдами из яиц, тостами, сырниками и всевозможными кашами на молоке. Основное меню начинает действовать с часу дня. На открытой кухне лепят несколько видов пасты: тальятелле, спагетти, феттучини и папарделле. Готовят и блюда из мяса и птицы вроде утиной грудки с копчёной свёклой. В дополнение — лаконичная подборка вин по бокалам и по бутылкам, коктейли и крепкий алкоголь.                            ",
    "features": [
        "чаевые онлайн",
        "завтрак"
    ],
    "kitchen": [
        "европейская",
        "итальянская"
    ],
    "main_image_url": "friends-of-friends+main_image.jpg",
    "main_url": "https://www.restoclub.ru",
    "menu": "complete",
    "name": "Friends of Friends",
    "phone": "+78122007300",
    "timetable": "Пн–Чт: 09:00 — 23:00Пт–Сб: 09:00 — 01:00Вс: 09:00 — 23:00"
}