{
    "Coordinates": [
        "59.92195800",
        "30.34868400"
    ],
    "additional_url": "/spb/place/good-news-coffee",
    "address": "Боровая ул. 6",
    "album": "complete",
    "avg_check": "1000  (без напитков)",
    "category": "Кофейня",
    "description": "\n                Дог-френдли кофейня с веганскими десертами на Боровой улице. Список напитков стандартный: готовят американо, капучино, латте, раф, флэт уайт. Особенно в кофейне «Гуд ньюс» гордятся собственной выпечкой и десертами, в числе последних — веганские торты и пирожные без продуктов животного происхождения. Из интересного на кондитерской витрине — сыроедческие чизкейки. Коржи для них делают из фиников и молотых семян льна, а начинка представляет собой крем из сушеных орехов, ягод, кокосового молока и сиропа топинамбура. Для более плотного перекуса можно взять киши. В кофейне рады гостям с домашними питомцами.                            ",
    "features": [
        "можно с животными",
        "завтрак",
        "кулинарные мастер-классы"
    ],
    "kitchen": [
        "вегетарианская",
        "десерты",
        "европейская"
    ],
    "main_image_url": "good-news-coffee+main_image.jpg",
    "main_url": "https://www.restoclub.ru",
    "menu": "complete",
    "name": "Good News",
    "phone": "+79313580172",
    "timetable": "Пн–Чт: 09:00 — 22:00Пт–Сб: 09:00 — 23:00Вс: 09:00 — 22:00"
}