{
    "Coordinates": [
        "60.12247000",
        "29.97103200"
    ],
    "additional_url": "/spb/place/gost",
    "address": "Заречная дорога 19",
    "album": "complete",
    "avg_check": "2500  (без напитков)",
    "category": "Ресторан",
    "description": "\n                Gostь — двухуровневый ресторан с террасой при отеле «Золотой ручей» в Сестрорецке. \r\nВ интерьере использовали светлые мягкие тона и элементы из древесной текстуры, чтобы посетители могли полностью погрузиться в атмосферу загородного дома и почувствовать единение с природой. На кухне готовят преимущественно блюда европейской кухни, отдавая предпочтение фермерским продуктам. Здесь каждый гость найдет блюдо по душе. Целый день проходят завтраки, а меню а-ля карт начинает действовать с 12 часов дня.                            ",
    "features": [
        "при отеле",
        "за городом",
        "завтрак"
    ],
    "kitchen": [
        "европейская"
    ],
    "main_image_url": "gost+main_image.jpg",
    "main_url": "https://www.restoclub.ru",
    "menu": "complete",
    "name": "Gostь",
    "phone": "+79313204444",
    "timetable": "Пн–Вс: 08:00 — 22:00"
}