{
    "Coordinates": [
        "59.92740100",
        "30.32333300"
    ],
    "additional_url": "/spb/place/kiki-1",
    "address": "ул. Гороховая 47",
    "album": "complete",
    "avg_check": "400  (без напитков)",
    "category": "Бар",
    "description": "\n                Kiki — атмосферный бар с израильскими закусками и вечеринками на Гороховой улице.\r\nВнутри — стильное помещение в стиле лофт с приятными ностальгическими вайбами: ламповые телевизоры в качестве декора, советский стационарный телефон, неоновые вывески. В компактном меню — израильская кухня: дёнеры и хумус, а также суп из чечевицы и парочка сезонных блюд. В дополнение — пиво или коктейли.                            ",
    "features": [
        "еда навынос",
        "dj"
    ],
    "kitchen": [
        "израильская",
        "восточная"
    ],
    "main_image_url": "kiki-1+main_image.jpg",
    "main_url": "https://www.restoclub.ru",
    "menu": "complete",
    "name": "Kiki",
    "phone": "+79006317373",
    "timetable": "Пн–Чт: 15:00 — 00:00Пт–Сб: 13:00 — 02:00Вс: 15:00 — 00:00"
}