{
    "Coordinates": [
        "55.76131475",
        "37.64323629"
    ],
    "additional_url": "/msk/place/kiosk-1936",
    "address": "Чистопрудный б-р 12, с.4",
    "avg_check": "1000  (без напитков)",
    "category": "Кафе",
    "description": "\n                Кофейня на Чистопрудном бульваре от создателей From Berlin. В «Киоске 1936» готовят кофейные напитки вроде капучино, латте и флэт уайт, и заваривают фильтр-кофе и пуровер. В меню есть чай, фреши и сидр. Помимо напитков на закуску предлагают бриошь с лососем или мортаделлой, тост с хумусом и десерты. В винной карте представили натуральные, органические и биодинамические вина из небольших европейских винодельческих хозяйств.                            ",
    "features": [
        "чаевые онлайн",
        "завтрак"
    ],
    "kitchen": [
        "десерты"
    ],
    "main_image_url": "",
    "main_url": "https://www.restoclub.ru",
    "name": "Kiosk 1936",
    "phone": "+79997150826",
    "timetable": "Пн–Вс: 09:00 — 23:00"
}