{
    "Coordinates": [
        "55.72779000",
        "37.62351900"
    ],
    "additional_url": "/msk/place/kortiger",
    "address": "ул. Люсиновская 13/1",
    "avg_check": "900  (без напитков)",
    "category": "Кафе",
    "description": "\n                Корейское кафе на Люсиновской улице. В меню хиты азиатской кухни: в качестве стартеров креветки васаби, хот- и корн-доги, на горячее варят разные вариации мисо, например, с лососем или курицей, готовят токпокки (рисовые клецки) в остром соусе и стеклянную лапшу чапче с креветками или говядиной. Выпить предлагают корейские алкогольные напитки вроде Соджу и пива, из безалкогольного — широкий выбор бабл ти.                            ",
    "features": [
        "еда навынос",
        "здесь танцуют",
        "бизнес-ланч",
        "dj",
        "доставка"
    ],
    "kitchen": [
        "корейская",
        "азиатская"
    ],
    "main_image_url": "",
    "main_url": "https://www.restoclub.ru",
    "name": "Kortiger",
    "phone": "+79299831288",
    "timetable": "Пн–Вс: 11:00 — 23:00"
}