{
    "Coordinates": [
        "55.76320400",
        "37.59470100"
    ],
    "additional_url": "/msk/place/mama-tuta-1",
    "address": "ул. Малая Бронная 24 с. 1",
    "avg_check": "2100  (без напитков)",
    "category": "Ресторан",
    "description": "\n                «Мама тута» — грузинский ресторан Арама Мнацаканова на Патриарших. \r\nПроект сначала открыли в Петербурге, а затем успешно перенесли в Москву. Внутри — атмосферное оформление с аутентичными деталями от сестер Сундуковых. \r\nВ лаконичном меню представлены национальные хиты и авторские вариации на тему грузинской кухни — баже с курицей, миниатюрные хинкали, румяные пеновани с сыром. В утреннем меню есть и грузинские блюда, и классические омлеты и блинчики. \r\nВ дополнение — домашние лимонады и фирменный чай, а в барной карте представили подборку европейских вин, чачу и фруктовую водку, а также классические коктейли.                            ",
    "features": [
        "еда навынос",
        "чаевые онлайн",
        "завтрак"
    ],
    "kitchen": [
        "грузинская",
        "кавказская"
    ],
    "main_image_url": "",
    "main_url": "https://www.restoclub.ru",
    "name": "Мама тута",
    "phone": "+74993994090",
    "timetable": "Пн–Пт: 09:00 — 00:30Сб–Вс: 10:00 — 00:30"
}