{
    "Coordinates": [
        "55.65137900",
        "37.61238900"
    ],
    "additional_url": "/msk/place/myasoroob",
    "address": "б-р Чонгарский 7",
    "avg_check": "600  (без напитков)",
    "category": "Кафе",
    "description": "\n                Сетевая бургерная в РЦ «Ангара». «Мясоroob» — ресторан быстрого питания, в котором кроме популярных позиций подают фирменные блюда. В меню классические бургеры, а также острый с перцем халапеньо и соленым огурцом, сытный с яичницей глазуньей и рваный — с томлёной мраморной грудинкой. Для тех, кто не ест мясо, готовят вегетарианские бургеры. Также в бургерной «Мясоруб» подают стейки, свиные ребрышки, гарниры. По будням с 11:00 подают бизнес-ланчи. Для маленьких гостей действует детское меню. Работает служба доставки.                            ",
    "features": [
        "детское меню",
        "бизнес-ланч",
        "доставка"
    ],
    "kitchen": [
        "американская",
        "европейская",
        "бургеры"
    ],
    "main_image_url": "",
    "main_url": "https://www.restoclub.ru",
    "name": "Мясоroob",
    "phone": "+78005008393",
    "timetable": "Пн–Вс: 10:00 — 22:00"
}