{
    "Coordinates": [
        "55.77780800",
        "37.66969300"
    ],
    "additional_url": "/msk/place/nastojkin",
    "address": "ул. Нижняя Красносельская 13, с.1",
    "avg_check": "750  (без напитков)",
    "category": "Ресторан",
    "description": "\n                «Настойкин» — рестобар с фиксированными ценами в районе «Красносельской». Среди исторических интерьеров здесь подают закуски по демократичным ценам и наливают фирменные настойки.\r\n \r\nВ сытное меню бара вошли популярные блюда разных стран мира от США до Азии. Гостям подают сочные бургеры, хрустящие свиные ребрышки и наваристые супы, например, русский борщ. Большой раздел посвятили закускам от изысканных морепродуктов до жареных пельменей. Все позиции отдают всего за 250 рублей!\r\n \r\nОтдельная гордость команды — подборка настоек. Среди 15 вкусов — привычный лимончелло и хреновуха, оригинальный пало санто с бергамотом, тропический манго или нежная клубника. Кроме настоек, предлагают оценить подборку европейских вин, классических коктейлей и крепких позиций вроде виски.\r\n \r\nВ историческом здании Москвы расположился бар «Настойкин». Отдавая дань традициям, тут сохранили кирпичную кладку и винтовую лестницу, дополнив антураж деталями в стиле лофт: зелеными растениями и камерным светом ламп.\r\n \r\nОтметить праздник ярко и незабываемо поможет команда бара. Все залы легко закрыть целиком под событие, где с комфортом разместится до 50 гостей. Приятный бонус — при «Настойкине» открыта собственная парковка.                                    \n    Текст предоставлен заведением",
    "features": [],
    "kitchen": [
        "коктейли",
        "русская",
        "крафтовое пиво",
        "европейская"
    ],
    "main_image_url": "",
    "main_url": "https://www.restoclub.ru",
    "name": "Настойкин",
    "phone": "+74958856348",
    "timetable": "Пн–Чт: 12:00 — 00:00Пт–Сб: 12:00 — 02:00Вс: 12:00 — 00:00"
}