{
    "Coordinates": [
        "55.71234100",
        "37.62621000"
    ],
    "additional_url": "/msk/place/om-chajnaja-studija",
    "address": "Павловская 18а",
    "avg_check": "700  (без напитков)",
    "category": "Ресторан",
    "description": "\n                Чайная с регулярными церемониями на территории центра йоги «Открытый мир». Пространство заведения оформлено на азиатский манер с бамбуковыми перегородками, изображениями и статуэтками божеств. Гостям предлагают расположиться на полу у чабанов — это небольшие столики с поддоном, предусмотренные для чайных церемоний. Один такой ритуал может длиться около двух часов. В меню представлены элитные сорта черного, зеленого, белого, цветочного чая, есть небольшой выбор сладостей. При «Чайной студии» работает школа китайского чайного мастерства Шамиля Пею. Для полноценного перекуса в «Открытом мире» имеется вегетарианское кафе.                            ",
    "features": [],
    "kitchen": [
        "индийская",
        "европейская"
    ],
    "main_image_url": "",
    "main_url": "https://www.restoclub.ru",
    "name": "ОМ / Чайная студия",
    "phone": "+79262679722",
    "timetable": "Пн–Пт: 12:00 — 22:00Сб–Вс: 12:00 — 23:00"
}