{
    "Coordinates": [
        "55.76034200",
        "37.59696500"
    ],
    "additional_url": "/msk/place/onest",
    "address": "ул. Малая Бронная 8с1",
    "avg_check": "2900  (без напитков)",
    "category": "Ресторан",
    "description": "\n                Ресторан Аркадия Новикова на Малой Бронной улице. «Онест» находится на втором этаже итальянского ресторана от Novikov Group «Аист». За меню отвечает шеф-повар Мирко Дзаго (Bro&N, «Аист»). «Онест» держит курс на Италию, но в более сложном формате: с ферментацией продуктов, сочетанием разных текстур и эффектной подачей блюд. В основу легли ингредиенты, традиционные для Средиземноморья. Попасть в ресторан Onest можно только по брони.                            ",
    "features": [],
    "kitchen": [
        "авторская"
    ],
    "main_image_url": "",
    "main_url": "https://www.restoclub.ru",
    "name": "Onest",
    "phone": "+79854707030",
    "timetable": "Пн–Вс: 12:00"
}