{
    "Coordinates": [
        "55.78836800",
        "37.61808400"
    ],
    "additional_url": "/msk/place/oxus",
    "address": "ул. Трифоновская 24, стр. 1",
    "avg_check": "2000  (без напитков)",
    "category": "Ресторан",
    "description": "\n                Элегантный ресторан восточной кухни в Мариной Роще. Здесь традиционные, приготовленные по всем правилам восточной кулинарии блюда подают в современном европейском антураже. Кухню возглавляет опытный шеф-повар из Узбекистана Боходир Нурмухамедов. Интерьер ресторана оформлен в освежающих светлых тонах. В Oxus шесть залов: два вместительных основных; два камерных, каждый из которых рассчитан на пятнадцать человек и снабжен собственной кухней; небольшая мансарда и закрытая веранда с выходом во двор.                            ",
    "features": [
        "чаевые онлайн"
    ],
    "kitchen": [
        "восточная"
    ],
    "main_image_url": "",
    "main_url": "https://www.restoclub.ru",
    "name": "Oxus",
    "phone": "+74956818000",
    "timetable": "Пн–Вс: 12:00 — 00:00"
}