{
    "Coordinates": [
        "59.77231000",
        "30.13945700"
    ],
    "additional_url": "/spb/place/pushkin-cake",
    "address": "ул. Московская 5",
    "album": "complete",
    "avg_check": "800  (без напитков)",
    "category": "Кондитерская",
    "description": "\n                Уютное кафе-кондитерская в Пушкине. Интерьер Pushkin Cake выполнен в теплых шоколадно-кофейных тонах, стены украшают милые безделушки и рисунки сладостей. В меню большой выбор всевозможных десертов: капкейки, имбирные печенья, ягодные тарты. Кроме того, можно плотно пообедать, заказав суп, салат или пиццу. В кондитерской изготавливают торты по индивидуальным эскизам. В «Пушкине» целый день действуют комплексные завтраки. Периодически в кафе устраивают тематические праздники для детей.                            ",
    "features": [
        "за городом",
        "детское меню",
        "завтрак"
    ],
    "kitchen": [
        "десерты",
        "европейская"
    ],
    "main_image_url": "pushkin-cake+main_image.jpg",
    "main_url": "https://www.restoclub.ru",
    "menu": "complete",
    "name": "Pushkin Cake",
    "phone": "+79312296499",
    "timetable": "Пн–Чт: 08:00 — 21:00Пт–Вс: 08:00 — 22:00"
}