{
    "Coordinates": [
        "55.75502300",
        "37.64430600"
    ],
    "additional_url": "/msk/place/repej",
    "address": "Большой Трёхсвятительский пер. д.2/1 с.9",
    "avg_check": "no_avg_check",
    "category": "Рюмочная",
    "description": "\n                Камерная рюмочная в районе Китай-города. Под кирпичными сводами исторического здания разместили три стола и барную стойку. Здесь готовят и наливают фирменные настойки по собственным рецептам. В барной карте предлагают попробовать настойки на дыне и лемонграссе, на свекле и какао-бобах, на кинзе с медом и малине с эстрагоном. Помимо настоек подают вино и крепкие алкогольные напитки, если возникнут трудности с выбором гостям поможет штатный сомелье.                            ",
    "features": [],
    "kitchen": [],
    "main_image_url": "",
    "main_url": "https://www.restoclub.ru",
    "name": "Репей",
    "phone": "+79255750013",
    "timetable": "Пн–Вс: 15:00 — 00:00"
}