{
    "Coordinates": [
        "55.77394791",
        "37.57772961"
    ],
    "additional_url": "/msk/place/rezolute",
    "address": "ул. Грузинский Вал 11с4",
    "avg_check": "3200  (без напитков)",
    "category": "Ресторан",
    "description": "\n                Камерный ресторан на Грузинском Валу. Название отсылает к президентскому столу в Белом доме. Концепция проекта необычна для Москвы. «Резолют» — это ресторан одного стола. Интерьер просторного зала с изумрудно-зелеными креслами выполнен с элементами ар-деко. Пространство дополняют камин с живым огнем и лаунж-зона. Главный объект — большой круглый стол на 12 человек. Зал расчитан только на одну компанию. Во время ужина гости вольны делать все, что захочется. В меню авторские средиземноморские блюда, разработанные Рафаэлем Казумяном, выпускником кулинарной школы Le Cordon Blue.                            ",
    "features": [],
    "kitchen": [
        "средиземноморская",
        "европейская",
        "авторская"
    ],
    "main_image_url": "",
    "main_url": "https://www.restoclub.ru",
    "name": "Rezolute",
    "phone": "+74950321700",
    "timetable": "Пн–Вс: Под заказ"
}