{
    "Coordinates": [
        "59.90981500",
        "30.34570100"
    ],
    "additional_url": "/spb/place/sahara-6",
    "address": "ул. Прилукская 15",
    "album": "complete",
    "avg_check": "1200  (без напитков)",
    "category": "Ресторан",
    "description": "\n                Ресторан восточной кухни на Прилукской улице. В ресторане «Сахара» концепцию построили вокруг традиционных блюд Ближнего Востока. К примеру, здесь можно попробовать хумус или кофту — мясное блюдо из двух видов фарша. Специальный раздел посвятили специалитетам, приготовленным на мангале вроде шашлыков и люля-кебаб. На кухне в печи делают национальные лепешки и запекают мясо. Гости могут попробовать рыбу и стейки, сделанные на углях. В течение всего дня подают завтраки. Пространство оформили в светлых бежевых оттенках, гости могут занять места на мягких креслах и диванах.                            ",
    "features": [],
    "kitchen": [
        "восточная"
    ],
    "main_image_url": "sahara-6+main_image.jpg",
    "main_url": "https://www.restoclub.ru",
    "menu": "complete",
    "name": "Sahara",
    "phone": "+79111484704",
    "timetable": "Пн–Вс: 09:00 — 03:30"
}