{
    "Coordinates": [
        "59.93883001",
        "30.32309914"
    ],
    "additional_url": "/spb/place/sakvojazh-dlja-beremennoj-shpionki",
    "address": "ул. Большая Конюшенная 17",
    "album": "complete",
    "avg_check": "1500  (без напитков)",
    "category": "Бар",
    "description": "\n                «Саквояж беременной шпионки» — бар-развлечение в шпионской тематике на Большой Конюшенной улице.\r\nИнтерьер насыщен деталями и подробностями шпионской жизни. Он, скорее всего, напоминает пыточную, но успокойтесь, здесь не страшно — это самый обычный чёрный юмор. Стол сделан в виде гроба, в котором под стеклом находится гипсовая голова, из барной стойки торчит часть женского тела со связанными конечностями. Здесь есть зал с приглушённым красным светом, где большая роспись на стене напоминает сцену из «Камасутры». И это далеко не всё.\r\nВ барной карте — пиво по бутылкам и на розлив, вино, крепкий алкоголь и алкогольные сеты. В дополнение — полноценное меню с затейливыми названиями блюд. На закуску — соленья, мясные и сырные тарелки, на горячее — паста карбонара или запечённая форель.                            ",
    "features": [
        "здесь танцуют",
        "живая музыка",
        "шоу-программа",
        "бизнес-ланч"
    ],
    "kitchen": [
        "европейская",
        "смешанная"
    ],
    "main_image_url": "sakvojazh-dlja-beremennoj-shpionki+main_image.jpg",
    "main_url": "https://www.restoclub.ru",
    "menu": "complete",
    "name": "Саквояж беременной шпионки",
    "phone": "+79219509516",
    "timetable": "Пн–Чт: 11:00 — 01:00Пт–Сб: 12:00 — 02:00Вс: 11:00 — 01:00"
}