{
    "Coordinates": [
        "59.94380188",
        "30.35230064"
    ],
    "additional_url": "/spb/place/schengen",
    "address": "ул. Кирочная 5",
    "album": "complete",
    "avg_check": "1450  (без напитков)",
    "category": "Ресторан",
    "description": "\n                Стильный европейский ресторан с легким модерновым интерьером. Меню заведения так же лаконично и изящно, как его внутреннее убранство: тут собраны блюда европейской, азиатской, восточной и израильской кухонь в авторской интерпретации шеф-повара. На закуску готовят тартары и брускетты, из основных блюд подают утку, филе оленя и томленую шею ягненка. В списке десертов значится карамельный бисквит, бриошь с камамбером и шоколадный мусс. В первом зале ресторана можно устроиться у больших витринных окон, здесь же располагается детская комната.                            ",
    "features": [
        "чаевые онлайн",
        "детское меню",
        "детская комната",
        "бизнес-ланч"
    ],
    "kitchen": [
        "европейская",
        "смешанная"
    ],
    "main_image_url": "schengen+main_image.jpg",
    "main_url": "https://www.restoclub.ru",
    "menu": "complete",
    "name": "Schengen",
    "phone": "+78129221197",
    "timetable": "Пн–Пт: 09:00 — 00:00Сб–Вс: 11:00 — 00:00"
}