{
    "Coordinates": [
        "55.82666812",
        "37.57167819"
    ],
    "additional_url": "/msk/place/shum-goroda",
    "address": "ш. Дмитровское 27",
    "avg_check": "1000  (без напитков)",
    "category": "Кафе",
    "description": "\n                Круглосуточный ресторан недалеко от Мичуринского сада. «Шум города» расположен на 1 этаже отеля Park Tower. Одно из преимуществ ресторана — панорамные окна с видом на окрестности. В меню обошлись без экспериментов. В списке европейские горячие и холодные закуски, пицца, паста, привычные блюда из мяса и рыбы. Из интересного — десерты собственного приготовления, в ней более 15 видов тортов и пирогов. В барной карте дежурный набор из вин на каждый день, немецкого пива и шотландского виски. Мешают коктейли вроде «Пина колады» и «Голубой лагуны».                            ",
    "features": [
        "при отеле",
        "панорамный вид",
        "парковка"
    ],
    "kitchen": [
        "европейская"
    ],
    "main_image_url": "",
    "main_url": "https://www.restoclub.ru",
    "name": "Шум города",
    "phone": "+74999773422",
    "timetable": "Пн–Вс: 11:00 — 00:00"
}