{
    "Coordinates": [
        "55.76361108",
        "37.60650917"
    ],
    "additional_url": "/msk/place/syto-piano-3",
    "address": "ул. Тверская 17",
    "avg_check": "1000  (без напитков)",
    "category": "Кафе",
    "description": "\n                «Сыто Piano»‎ — cетевое демократичное кафе на Тверской. \r\nВ «Сыто Piano» подготовили многостраничное меню с европейскими и азиатскими блюдами. Здесь готовят бургеры из говяжьей или куриной котлеты, стейки из мраморной говядины, итальянскую пасту, японские роллы, шашлыки. Последние готовятся на углях и подаются с лавашом и овощами. Параллельно здесь можно заказать пиццу, любой вариант дополняют на выбор классическим томатным соусом, барбекю или соусом песто.                            ",
    "features": [
        "чаевые онлайн",
        "dj",
        "кальян"
    ],
    "kitchen": [
        "европейская",
        "бургеры",
        "смешанная",
        "американская",
        "суши",
        "пицца"
    ],
    "main_image_url": "",
    "main_url": "https://www.restoclub.ru",
    "name": "Сыто Piano",
    "phone": "+79778006081",
    "timetable": "Пн–Вс: 11:00 — 06:00"
}