{
    "Coordinates": [
        "55.87106700",
        "37.60984700"
    ],
    "additional_url": "/msk/place/zolotaja-roshha",
    "address": "ул. Бестужевых 14, корп. 1",
    "avg_check": "1500  (без напитков)",
    "category": "Ресторан",
    "description": "\n                Помпезный банкетный ресторан в Отрадном. Заведение ориентировано на мероприятия различного \r\nформата, но по будням работает как ресторан «а ля карт». В «Золотой роще» два зала: «Серебряный» \r\nна 250 персон и «Золотой» на 180 гостей. В меню преимущественно европейская кухня. Есть раздел с \r\nкавказскими блюдами и едой, приготовленной на углях. Интерьер выполнен в стиле ампир с богатыми \r\nэлементами декора: золотая отделка, ламбрекены на шторах, резные колонны. В теплое время года на \r\nплощадке у ресторана открывается просторная терраса.                            ",
    "features": [
        "живая музыка",
        "бизнес-ланч",
        "доставка",
        "парковка"
    ],
    "kitchen": [
        "смешанная",
        "европейская"
    ],
    "main_image_url": "",
    "main_url": "https://www.restoclub.ru",
    "name": "Золотая роща",
    "phone": "+74959026061",
    "timetable": "Пн–Чт: 12:00 — 00:00Пт–Сб: 12:00 — 01:00Вс: 12:00 — 00:00"
}